setup.py
asposeocrcloud/ApiClient.py
asposeocrcloud/OcrApi.py
asposeocrcloud/__init__.py
asposeocrcloud.egg-info/PKG-INFO
asposeocrcloud.egg-info/SOURCES.txt
asposeocrcloud.egg-info/dependency_links.txt
asposeocrcloud.egg-info/requires.txt
asposeocrcloud.egg-info/top_level.txt
asposeocrcloud/models/OCRResponse.py
asposeocrcloud/models/PagesInfo.py
asposeocrcloud/models/PartsInfo.py
asposeocrcloud/models/__init__.py
tests/__init__.py
tests/test_OcrApi.py